penn_chime/__init__.py
penn_chime/cli.py
penn_chime/constants.py
penn_chime/utils.py
tests/__init__.py
tests/conftest.py
penn_chime-1.1.3.dist-info/LICENSE.txt
penn_chime-1.1.3.dist-info/METADATA
penn_chime-1.1.3.dist-info/WHEEL
penn_chime-1.1.3.dist-info/entry_points.txt
penn_chime-1.1.3.dist-info/top_level.txt
penn_chime-1.1.3.dist-info/RECORD
