Metadata-Version: 2.1
Name: penn-chime
Version: 1.1.3
Summary: Covid-19 Hospital Impact Model for Epidemics
Home-page: https://codeforphilly.github.io/chime/
Author: Predictive Healthcare @ Penn Medicine
Author-email: 
License: UNKNOWN
Platform: UNKNOWN
Classifier: Programming Language :: Python :: 3
Classifier: License :: OSI Approved :: MIT License
Classifier: Operating System :: OS Independent
Requires-Python: >=3.7
